README.md
setup.py
webcollector/__init__.py
webcollector/config.py
webcollector/crawler.py
webcollector/db_manager.py
webcollector/fetch.py
webcollector/filter.py
webcollector/generate.py
webcollector/model.py
webcollector/net.py
webcollector/utils.py
webcollector.egg-info/PKG-INFO
webcollector.egg-info/SOURCES.txt
webcollector.egg-info/dependency_links.txt
webcollector.egg-info/requires.txt
webcollector.egg-info/top_level.txt
webcollector/plugin/__init__.py
webcollector/plugin/net.py
webcollector/plugin/ram.py
webcollector/plugin/redis.py