Metadata-Version: 1.0
Name: webcollector
Version: 0.0.5a0
Summary: WebCollector-Python is an open source web crawler framework based on Python.It provides some simple interfaces for crawling the Web,you can setup a multi-threaded web crawler in less than 5 minutes.
Home-page: https://github.com/CrawlScript/WebCollector-Python
Author: Jun Hu
Author-email: UNKNOWN
License: GNU General Public License v3.0 (See LICENSE)
Platform: UNKNOWN
